arcade_hubspot_crm_api/__init__.py
arcade_hubspot_crm_api/moar/hubspot_crm.json
arcade_hubspot_crm_api/moar/openapi.json
arcade_hubspot_crm_api/tools/__init__.py
arcade_hubspot_crm_api/tools/request_body_schemas.py
arcade_hubspot_crm_api/wrapper_tools/AddAllFromSourceListToDestinationList.json
arcade_hubspot_crm_api/wrapper_tools/AddToHubspotCrmList.json
arcade_hubspot_crm_api/wrapper_tools/ArchiveCallInHubspot.json
arcade_hubspot_crm_api/wrapper_tools/ArchiveCallsBatch.json
arcade_hubspot_crm_api/wrapper_tools/ArchiveCartsBatch.json
arcade_hubspot_crm_api/wrapper_tools/ArchiveCommercePaymentsBatch.json
arcade_hubspot_crm_api/wrapper_tools/ArchiveCommunication.json
arcade_hubspot_crm_api/wrapper_tools/ArchiveContactsBatch.json
arcade_hubspot_crm_api/wrapper_tools/ArchiveCoursesBatch.json
arcade_hubspot_crm_api/wrapper_tools/ArchiveCrmProperties.json
arcade_hubspot_crm_api/wrapper_tools/ArchiveDealInHubspot.json
arcade_hubspot_crm_api/wrapper_tools/ArchiveDiscountsBatch.json
arcade_hubspot_crm_api/wrapper_tools/ArchiveEmailsBatch.json
arcade_hubspot_crm_api/wrapper_tools/ArchiveFeesBatch.json
arcade_hubspot_crm_api/wrapper_tools/ArchiveGoalTargetsBatch.json
arcade_hubspot_crm_api/wrapper_tools/ArchiveHubspotLead.json
arcade_hubspot_crm_api/wrapper_tools/ArchiveHubspotObjectsBatch.json
arcade_hubspot_crm_api/wrapper_tools/ArchiveHubspotTasks.json
arcade_hubspot_crm_api/wrapper_tools/ArchiveInvoicesBatch.json
arcade_hubspot_crm_api/wrapper_tools/ArchiveLeadsBatch.json
arcade_hubspot_crm_api/wrapper_tools/ArchiveLineItemsBatch.json
arcade_hubspot_crm_api/wrapper_tools/ArchiveMeetingsBatch.json
arcade_hubspot_crm_api/wrapper_tools/ArchiveMultipleAppointments.json
arcade_hubspot_crm_api/wrapper_tools/ArchiveMultipleDeals.json
arcade_hubspot_crm_api/wrapper_tools/ArchiveMultipleListings.json
arcade_hubspot_crm_api/wrapper_tools/ArchiveNotesBatch.json
arcade_hubspot_crm_api/wrapper_tools/ArchiveOrdersBatch.json
arcade_hubspot_crm_api/wrapper_tools/ArchivePostalMail.json
arcade_hubspot_crm_api-1.0.0.dist-info/METADATA
arcade_hubspot_crm_api-1.0.0.dist-info/WHEEL
arcade_hubspot_crm_api-1.0.0.dist-info/entry_points.txt
arcade_hubspot_crm_api-1.0.0.dist-info/licenses/LICENSE
arcade_hubspot_crm_api-1.0.0.dist-info/RECORD
